Workbook
Name Scenario: Assumptions!$B$8

Sheet IS26
A1: Created by EDGAR Online, Inc.
A3: SALESFORCE, INC.
A4: INCOME_STATEMENT
A5: Form Type: 10-K
A6: Period End: Jan 31, 2026
A7: Date Filed: Mar 02, 2026
A8: Table Of Contents
B10: Salesforce, Inc.
B11: Consolidated Statements of Operations
B12: (in millions, except per share data)
B13: 4 | C13: Fiscal Year Ended January 31,
C14: 2026 | D14: 2025 | E14: 2024 | F14: 2023 | G14: 2022
B15: Revenues:
B16: Subscription and support | C16: 39388 | D16: 35679 | E16: 32537 | F16: 29021 | G16: 24657
B17: Professional services and other | C17: 2137 | D17: 2216 | E17: 2320 | F17: 2331 | G17: 1835
B18: Total revenues | C18: 41525 | D18: 37895 | E18: 34857 | F18: 31352 | G18: 26492
B19: Cost of revenues (1)(2):
B20: Subscription and support | C20: 6796 | D20: 6198 | E20: 6177 | F20: 5821 | G20: 5059
B21: Professional services and other | C21: 2474 | D21: 2445 | E21: 2364 | F21: 2539 | G21: 1967
B22: Total cost of revenues | C22: 9270 | D22: 8643 | E22: 8541 | F22: 8360 | G22: 7026
B23: Gross profit | C23: 32255 | D23: 29252 | E23: 26316 | F23: 22992 | G23: 19466
B24: Operating expenses (1)(2):
B25: Research and development | C25: 5993 | D25: 5493 | E25: 4906 | F25: 5055 | G25: 4465
B26: Sales and marketing | C26: 14345 | D26: 13257 | E26: 12877 | F26: 13526 | G26: 11855
B27: General and administrative | C27: 3000 | D27: 2836 | E27: 2534 | F27: 2553 | G27: 2598
B28: Restructuring | C28: 586 | D28: 461 | E28: 988 | F28: 828 | G28: 0
B30: Total operating expenses | C30: 23924 | D30: 22047 | E30: 21305 | F30: 21962 | G30: 18918
B31: Income from operations | C31: 8331 | D31: 7205 | E31: 5011 | F31: 1030 | G31: 548
B33: Gains (losses) on strategic investments, net | C33: 1017 | D33: -121 | E33: -277 | F33: -239 | G33: 1211
B34: Other income | C34: 172 | D34: 354 | E34: 216 | F34: -131 | G34: -227
B35: Income before provision for income taxes | C35: 9520 | D35: 7438 | E35: 4950 | F35: 660 | G35: 1532
B36: Provision for income taxes | C36: -2063 | D36: -1241 | E36: -814 | F36: -452 | G36: -88
B37: Net income | C37: 7457 | D37: 6197 | E37: 4136 | F37: 208 | G37: 1444
B39: Basic net income per share | C39: 7.85 | D39: 6.44 | E39: 4.25 | F39: 0.21 | G39: 1.51
... B42: Shares used in computing diluted net income per share | C42: 956 | D42: 974 | E42: 984 | F42: 997 | G42: 974

Sheet BS 2026
A1: Created by EDGAR Online, Inc.
A3: SALESFORCE, INC.
A4: BALANCE_SHEET
A5: Form Type: 10-K
A6: Period End: Jan 31, 2026
A7: Date Filed: Mar 02, 2026
A8: Table Of Contents
B10: Salesforce, Inc.
B11: Consolidated Balance Sheets
B12: (in millions)
C14: January 31,2026 | D14: January 31,2025 | E14: January 31, 2024 | F14: January 31, 2023 | G14: January 31, 2022
B16: Assets
B17: Current assets:
B18: Cash and cash equivalents | C18: 7327 | D18: 8848 | E18: 8472 | F18: 7016 | G18: 5464
B19: Marketable securities | C19: 2238 | D19: 5184 | E19: 5722 | F19: 5492 | G19: 5073
B20: Accounts receivable, net | C20: 14339 | D20: 11945 | E20: 11414 | F20: 10755 | G20: 9739
B21: Costs capitalized to obtain revenue contracts, net | C21: 2075 | D21: 1971 | E21: 1905 | F21: 1776 | G21: 1454
B22: Prepaid expenses and other current assets | C22: 2243 | D22: 1779 | E22: 1561 | F22: 1356 | G22: 1120
B23: Total current assets | C23: 28222 | D23: 29727 | E23: 29074 | F23: 26395 | G23: 22850
B24: Property and equipment, net | C24: 3120 | D24: 3236 | E24: 3689 | F24: 3702 | G24: 2815
B25: Operating lease right-of-use assets, net | C25: 2003 | D25: 2157 | E25: 2366 | F25: 2890 | G25: 2880
B26: Noncurrent costs capitalized to obtain revenue contracts, net | C26: 2985 | D26: 2475 | E26: 2515 | F26: 2697 | G26: 2342
B28: Strategic investments | C28: 7591 | D28: 4852 | E28: 4848 | F28: 4672 | G28: 4784
B29: Goodwill | C29: 57941 | D29: 51283 | E29: 48620 | F29: 48568 | G29: 47937
B30: Intangible assets acquired through business combinations, net | C30: 6815 | D30: 4428 | E30: 5278 | F30: 7125 | G30: 8978
... B32: Total assets | C32: 112305 | D32: 102928 | E32: 99823 | F32: 98849 | G32: 95209
B33: Liabilities and stockholders' equity
B34: Current liabilities:
B35: Accounts payable, accrued expenses and other liabilities | C35: 8253 | D35: 6658 | E35: 6111 | F35: 6743 | G35: 5470
B36: Operating lease liabilities, current | C36: 548 | D36: 579 | E36: 518 | F36: 590 | G36: 686
B37: Unearned revenue | C37: 24317 | D37: 20743 | E37: 19003 | F37: 17376 | G37: 15628
B39: Debt, current | C39: 4000 | D39: 0 | E39: 999 | F39: 1182 | G39: 4
B40: Total current liabilities | C40: 37118 | D40: 27980 | E40: 26631 | F40: 25891 | G40: 21788
B41: Noncurrent debt | C41: 10439 | D41: 8433 | E41: 8427 | F41: 9419 | G41: 10592
B42: Noncurrent operating lease liabilities | C42: 2189 | D42: 2380 | E42: 2644 | F42: 2897 | G42: 2703
B43: Other noncurrent liabilities | C43: 3417 | D43: 2962 | E43: 2475 | F43: 2283 | G43: 1995
B44: Total liabilities | C44: 53163 | D44: 41755 | E44: 40177 | F44: 40490 | G44: 37078
B45: Commitments and contingencies (See Notes 6 and 14)
B46: Stockholders' equity:
B47: Preferred stock, $0.001 par value; 5 shares authorized and none
B48: issued and outstanding | C48: 0 | D48: 0 | E48: 0 | F48: 0 | G48: 0
B49: Common stock, $0.001 par value; 1,600 shares authorized, 1,073 and
B50: 1,056 shares issued as of January 31, 2026 and 2025, respectively,
B51: and 929 and 962 shares outstanding as of January 31, 2026 and 2025,
B52: respectively | C52: 1 | D52: 1 | E52: 1 | F52: 1 | G52: 1
B54: Treasury stock, at cost | C54: -32228 | D54: -19507 | E54: -11692 | F54: -4000 | G54: 0
B55: Additional paid-in capital | C55: 68835 | D55: 64576 | E55: 59841 | F55: 55047 | G55: 50919
B56: Accumulated other comprehensive income (loss) | C56: 313 | D56: -266 | E56: -225 | F56: -274 | G56: -166
B57: Retained earnings | C57: 22221 | D57: 16369 | E57: 11721 | F57: 7585 | G57: 7377
B58: Total stockholders' equity | C58: 59142 | D58: 61173 | E58: 59646 | F58: 58359 | G58: 58131
B59: Total liabilities and stockholders' equity | C59: 112305 | D59: 102928 | E59: 99823 | F59: 98849 | G59: 95209

Sheet CF26
A1: Created by EDGAR Online, Inc.
A3: SALESFORCE, INC.
A4: CASH_FLOW
A5: Form Type: 10-K
A6: Period End: Jan 31, 2026
A7: Date Filed: Mar 02, 2026
A8: Table Of Contents
B10: Salesforce, Inc.
B11: Consolidated Statements of Cash Flows
B12: (in millions) | C12: Fiscal Year Ended
B13: 4 | C13: January 31,
C14: 2026 | D14: 2025 | E14: 2024 | F14: 2023 | G14: 2022
B15: Operating activities:
B16: Net income | C16: 7457 | D16: 6197 | E16: 4136 | F16: 208 | G16: 1444
B17: Adjustments to reconcile net income to net cash provided by
B18: operating activities:
B19: Depreciation and amortization (1) | C19: 3631 | D19: 3477 | E19: 3959 | F19: 3786 | G19: 3298
B20: Amortization of costs capitalized to obtain revenue
B21: contracts, net | C21: 2197 | D21: 2095 | E21: 1925 | F21: 1668 | G21: 1348
B22: Stock-based compensation expense | C22: 3509 | D22: 3183 | E22: 2787 | F22: 3279 | G22: 2779
B24: (Gains) losses on strategic investments, net | C24: -1017 | D24: 121 | E24: 277 | F24: 239 | G24: -1211
B26: Changes in assets and liabilities, net of business
B27: combinations:
B28: Accounts receivable, net | C28: -2160 | D28: -490 | E28: -659 | F28: -995 | G28: -1824
B29: Costs capitalized to obtain revenue contracts, net | C29: -2811 | D29: -2121 | E29: -1872 | F29: -2345 | G29: -2283
B30: Prepaid expenses and other current assets and other assets | C30: 819 | D30: -1495 | E30: -843 | F30: -302 | G30: 114
B32: Accounts payable and accrued expenses and other liabilities | C32: 1014 | D32: 1089 | E32: -478 | F32: 528 | G32: 507
B33: Operating lease liabilities | C33: -567 | D33: -548 | E33: -621 | F33: -699 | G33: -801
B34: Unearned revenue | C34: 2924 | D34: 1584 | E34: 1623 | F34: 1744 | G34: 2629
B35: Net cash provided by operating activities | C35: 14996 | D35: 13092 | E35: 10234 | F35: 7111 | G35: 6000
B36: Investing activities:
B37: Business combinations, net of cash acquired | C37: -9268 | D37: -2734 | E37: -82 | F37: -439 | G37: -14876
B38: Purchases of strategic investments | C38: -1958 | D38: -539 | E38: -496 | F38: -550 | G38: -1718
B39: Sales of strategic investments | C39: 184 | D39: 126 | E39: 108 | F39: 355 | G39: 2201
B40: Purchases of marketable securities | C40: -3763 | D40: -6879 | E40: -3761 | F40: -4777 | G40: -5674
B41: Sales of marketable securities | C41: 4414 | D41: 4143 | E41: 1511 | F41: 1771 | G41: 4179
B42: Maturities of marketable securities | C42: 2395 | D42: 3378 | E42: 2129 | F42: 2449 | G42: 2069
B43: Capital expenditures | C43: -594 | D43: -658 | E43: -736 | F43: -798 | G43: -717
B44: Net cash used in investing activities | C44: -8590 | D44: -3163 | E44: -1327 | F44: -1989 | G44: -14536
B45: Financing activities:
B46: Proceeds from issuance of debt, net of issuance costs | C46: 6000 | D46: 0 | E46: 0 | F46: 0 | G46: 7906
B47: Repayments of Slack Convertible Notes, net of capped call
B48: proceeds | F48: 0 | G48: -1197
B49: Repurchases of common stock | C49: -12596 | D49: -7829 | E49: -7620 | F49: -4000 | G49: 0
B50: Payments for taxes related to net share settlement of equity
B51: awards | C51: -351 | D51: 0 | E51: 0
B52: Proceeds from employee stock plans | C52: 1039 | D52: 1540 | E52: 1954 | F52: 861 | G52: 1289
B53: Principal payments on financing obligations | C53: -584 | D53: -603 | E53: -629 | F53: -419 | G53: -156
B54: Repayments of debt | C54: 0 | D54: -1000 | E54: -1182 | F54: -4 | G54: -4
B55: Payments of dividends and dividend equivalents | C55: -1587 | D55: -1537 | E55: 0
B56: Net cash used in financing activities | C56: -8079 | D56: -9429 | E56: -7477 | F56: -3562 | G56: 7838
B57: Effect of exchange rate changes | C57: 152 | D57: -124 | E57: 26 | F57: -8 | G57: -33
B58: Net increase (decrease) in cash and cash equivalents | C58: -1521 | D58: 376 | E58: 1456 | F58: 1552 | G58: -731
B59: Cash and cash equivalents, beginning of period | C59: 8848 | D59: 8472 | E59: 7016 | F59: 5464 | G59: 6195
B60: Cash and cash equivalents, end of period | C60: 7327 | D60: 8848 | E60: 8472 | F60: 7016 | G60: 5464

Sheet Forecasting
A1: Amount in millions
A2: Income statement | B2: 2021 | C2: 2022 | D2: 2023 | E2: 2024 | F2: 2025 | G2: 2026 | H2: 2027 | I2: 2028 | J2: 2029 | K2: 2030 | L2: 2031
A3: Revenue:
A4: Total Revenue | B4: 21252 | C4: ='IS26'!G16+'IS26'!G17 -> 26492 | D4: ='IS26'!F16+'IS26'!F17 -> 31352 | E4: ='IS26'!E16+'IS26'!E17 -> 34857 | F4: ='IS26'!D16+'IS26'!D17 -> 37895 | G4: ='IS26'!C16+'IS26'!C17 -> 41525 | H4: =G4*(1+Assumptions!B12) -> 45701.607 | I4: =H4*(1+Assumptions!C12) -> 50068.466 | J4: =I4*(1+Assumptions!D12) -> 54613.378 | K4: =J4*(1+Assumptions!E12) -> 59322.976 | L4: =K4*(1+Assumptions!F12) -> 64182.921
A5: COGS:
A6: Direct material/hosting/delivery | C6: ='IS26'!G20+'IS26'!G21 -> 7026 | D6: ='IS26'!F20+'IS26'!F21 -> 8360 | E6: ='IS26'!E20+'IS26'!E21 -> 8541 | F6: ='IS26'!D20+'IS26'!D21 -> 8643 | G6: ='IS26'!C20+'IS26'!C21 -> 9270 | H6: =H4*$G$121 -> 10202.382 | I6: =I4*$G$121 -> 11177.235 | J6: =J4*$G$121 -> 12191.837 | K6: =K4*$G$121 -> 13243.203 | L6: =L4*$G$121 -> 14328.132
A7: Direct labor
A8: Other direct costs
A9: Gross Profit | C9: =C4-C6 -> 19466 | D9: =D4-D6 -> 22992 | E9: =E4-E6 -> 26316 | F9: =F4-F6 -> 29252 | G9: =G4-G6 -> 32255 | H9: =H4-H6 -> 35499.226 | I9: =I4-I6 -> 38891.231 | J9: =J4-J6 -> 42421.541 | ... L9: =L4-L6 -> 49854.789
A10: Gross margin | C10: =C9/C4 -> 0.73478786 | D10: =D9/D4 -> 0.73335034 | E10: =E9/E4 -> 0.75497031 | F10: =F9/F4 -> 0.77192242 | G10: =G9/G4 -> 0.77676099 | H10: =H9/H4 -> 0.77676099 | I10: =I9/I4 -> 0.77676099 | J10: =J9/J4 -> 0.77676099 | ... L10: =L9/L4 -> 0.77676099
A12: Operating expenses:
A13: R&D | C13: ='IS26'!G25 -> 4465 | D13: ='IS26'!F25 -> 5055 | E13: ='IS26'!E25 -> 4906 | F13: ='IS26'!D25 -> 5493 | G13: ='IS26'!C25 -> 5993 | H13: =H4*Assumptions!B16 -> 6562.8003 | I13: =I4*Assumptions!C16 -> 7153.9365 | J13: =J4*Assumptions!D16 -> 7764.3109 | K13: =K4*Assumptions!E16 -> 8391.6989 | L13: =L4*Assumptions!F16 -> 9033.7802
A14: Sales & marketing | C14: ='IS26'!G26 -> 11855 | D14: ='IS26'!F26 -> 13526 | E14: ='IS26'!E26 -> 12877 | F14: ='IS26'!D26 -> 13257 | G14: ='IS26'!C26 -> 14345 | H14: =H4*Assumptions!B18 -> 15708.889 | I14: =I4*Assumptions!C18 -> 17123.848 | J14: =J4*Assumptions!D18 -> 18584.856 | K14: =K4*Assumptions!E18 -> 20086.588 | L14: =L4*Assumptions!F18 -> 21623.49
A15: G&A | C15: ='IS26'!G27 -> 2598 | D15: ='IS26'!F27 -> 2553 | E15: ='IS26'!E27 -> 2534 | F15: ='IS26'!D27 -> 2836 | G15: ='IS26'!C27 -> 3000 | H15: =H4*Assumptions!B20 -> 3285.2329 | I15: =I4*Assumptions!C20 -> 3581.1463 | J15: =J4*Assumptions!D20 -> 3886.6899 | K15: =K4*Assumptions!E20 -> 4200.7503 | L15: =L4*Assumptions!F20 -> 4522.166
A16: Other opex | C16: ='IS26'!G28 -> 0 | D16: ='IS26'!F28 -> 828 | E16: ='IS26'!E28 -> 988 | F16: ='IS26'!D28 -> 461 | G16: ='IS26'!C28 -> 586 | H16: =H4*Assumptions!B22 -> 641.7155 | I16: =I4*Assumptions!C22 -> 699.51723 | J16: =J4*Assumptions!D22 -> 759.2001 | K16: =K4*Assumptions!E22 -> 820.54656 | L16: =L4*Assumptions!F22 -> 883.32975
A17: Total opex | C17: =SUM(C13:C16) -> 18918 | D17: =SUM(D13:D16) -> 21962 | E17: =SUM(E13:E16) -> 21305 | F17: =SUM(F13:F16) -> 22047 | G17: =SUM(G13:G16) -> 23924 | H17: =SUM(H13:H16) -> 26198.638 | I17: =SUM(I13:I16) -> 28558.448 | J17: =SUM(J13:J16) -> 30995.057 | ... L17: =SUM(L13:L16) -> 36062.766
A18: EBITDA | C18: =C9-C17 -> 548 | D18: =D9-D17 -> 1030 | E18: =E9-E17 -> 5011 | F18: =F9-F17 -> 7205 | G18: =G9-G17 -> 8331 | H18: =H9-H17 -> 9300.588 | I18: =I9-I17 -> 10332.783 | J18: =J9-J17 -> 11426.485 | ... L18: =L9-L17 -> 13792.023
A19: Non-operating items:
A20: Interest income
A21: Interest expense
A22: Gains (losses) on strategic investments, net | C22: =+'IS26'!G33 -> 1211 | D22: =+'IS26'!F33 -> -239 | E22: ='IS26'!E33 -> -277 | F22: ='IS26'!D33 -> -121 | G22: ='IS26'!C33 -> 1017 | H22: 0 | I22: 0 | J22: 0 | K22: 0 | L22: 0
A23: Other income/(expense) | C23: ='IS26'!G34 -> -227 | D23: ='IS26'!F34 -> -131 | E23: =+'IS26'!E34 -> 216 | F23: =+'IS26'!D34 -> 354 | G23: =+'IS26'!C34 -> 172 | H23: =H4*Assumptions!B23 -> 189.29985 | I23: =I4*Assumptions!C23 -> 207.38774 | J23: =J4*Assumptions!D23 -> 226.21315 | K23: =K4*Assumptions!E23 -> 245.7207 | L23: =L4*Assumptions!F23 -> 265.85099
A25: Pre-tax income | C25: =C18+C23+C22 -> 1532 | D25: =D18+D23+D22 -> 660 | E25: =E18+E23+E22 -> 4950 | F25: =F18+F23+F22 -> 7438 | G25: =G18+G23+G22 -> 9520 | H25: =H18+H23+H22 -> 9489.8879 | I25: =I18+I23+I22 -> 10540.171 | J25: =J18+J23+J22 -> 11652.698 | ... L25: =L18+L23+L22 -> 14057.874
A26: Income tax expense | C26: =-'IS26'!G36 -> 88 | D26: =-'IS26'!F36 -> 452 | E26: =-'IS26'!E36 -> 814 | F26: =-'IS26'!D36 -> 1241 | G26: =-'IS26'!C36 -> 2063 | H26: =H25*Assumptions!B33 -> 2056.4747 | I26: =I25*Assumptions!C33 -> 2284.0728 | J26: =J25*Assumptions!D33 -> 2525.1592 | K26: =K25*Assumptions!E33 -> 2779.3964 | L26: =L25*Assumptions!F33 -> 3046.3649
A27: Net income | C27: =C25-C26 -> 1444 | D27: =D25-D26 -> 208 | E27: =E25-E26 -> 4136 | F27: =F25-F26 -> 6197 | G27: =G25-G26 -> 7457 | H27: =H25-H26 -> 7433.4132 | I27: =I25-I26 -> 8256.0982 | J27: =J25-J26 -> 9127.5387 | ... L27: =L25-L26 -> 11011.509
A28: Net income margin | C28: =C27/C4 -> 0.054507021 | D28: =D27/D4 -> 0.0066343455 | E28: =E27/E4 -> 0.11865622 | F28: =F27/F4 -> 0.16353081 | G28: =G27/G4 -> 0.17957857 | H28: =H27/H4 -> 0.16265102 | I28: =I27/I4 -> 0.16489617 | J28: =J27/J4 -> 0.16713009 | ... L28: =L27/L4 -> 0.17156447
A30: Balancesheet
A31: Assets:
A32: Current Assets
A33: CCE-marketable securities | B33: 6195 | C33: ='BS 2026'!G18 -> 5464 | D33: ='BS 2026'!F18 -> 7016 | E33: ='BS 2026'!E18 -> 8472 | F33: ='BS 2026'!D18 -> 8848 | G33: ='BS 2026'!C18 -> 7327 | H33: =H117 -> 6445.3961 | I33: =I117 -> 6372.5526 | J33: =J117 -> 6586.1215 | K33: =K117 -> 7882.2315 | L33: =L117 -> 10186.544
A34: Short term investment | C34: ='BS 2026'!G19 -> 5073 | D34: ='BS 2026'!F19 -> 5492 | E34: ='BS 2026'!E19 -> 5722 | F34: ='BS 2026'!D19 -> 5184 | G34: ='BS 2026'!C19 -> 2238 | H34: =MAX(0,-H75) -> 0 | I34: =MAX(0,-I75) -> 2167.6621 | J34: =MAX(0,-J75) -> 5136.3607 | K34: =MAX(0,-K75) -> 8267.8241 | L34: =MAX(0,-L75) -> 11690.226
A35: Accounts receivable | C35: ='BS 2026'!G20 -> 9739 | D35: ='BS 2026'!F20 -> 10755 | E35: ='BS 2026'!E20 -> 11414 | F35: ='BS 2026'!D20 -> 11945 | G35: ='BS 2026'!C20 -> 14339 | H35: =(Assumptions!B30*Forecasting!H4)/365 -> 15526.079 | I35: =(Assumptions!C30*Forecasting!I4)/365 -> 17009.62 | J35: =(Assumptions!D30*Forecasting!J4)/365 -> 18553.65 | K35: =(Assumptions!E30*Forecasting!K4)/365 -> 20153.629 | L35: =(Assumptions!F30*Forecasting!L4)/365 -> 21804.685
A36: Inventory
A37: Prepaid expenses | C37: ='BS 2026'!G22 -> 1120 | D37: ='BS 2026'!F22 -> 1356 | E37: ='BS 2026'!E22 -> 1561 | F37: ='BS 2026'!D22 -> 1779 | G37: ='BS 2026'!C22 -> 2243 | H37: =H4*(Assumptions!B35) -> 2113.8993 | I37: =I4*(Assumptions!C35) -> 2362.2033 | J37: =J4*(Assumptions!D35) -> 2628.1624 | K37: =K4*(Assumptions!E35) -> 2911.8987 | L37: =L4*(Assumptions!F35) -> 3213.4606
A38: Other CA | C38: ='BS 2026'!G21 -> 1454 | D38: ='BS 2026'!F21 -> 1776 | E38: ='BS 2026'!E21 -> 1905 | F38: ='BS 2026'!D21 -> 1971 | G38: ='BS 2026'!C21 -> 2075 | H38: =H4*Assumptions!B37 -> 2451.1189 | I38: =I4*Assumptions!C37 -> 2739.0335 | J38: =J4*Assumptions!D37 -> 3047.4198 | K38: =K4*Assumptions!E37 -> 3376.4191 | L38: =L4*Assumptions!F37 -> 3726.0876
A39: Total CA | C39: =SUM(C33:C38) -> 22850 | D39: =SUM(D33:D38) -> 26395 | E39: =SUM(E33:E38) -> 29074 | F39: =SUM(F33:F38) -> 29727 | G39: =SUM(G33:G38) -> 28222 | H39: =SUM(H33:H38) -> 26536.494 | I39: =SUM(I33:I38) -> 30651.072 | J39: =SUM(J33:J38) -> 35951.715 | ... L39: =SUM(L33:L38) -> 50621.003
A40: Non-Current assets
A41: PPE
A42: Accoumulated depreciation
A43: PPE, net | C43: ='BS 2026'!G24 -> 2815 | D43: ='BS 2026'!F24 -> 3702 | E43: ='BS 2026'!E24 -> 3689 | F43: ='BS 2026'!D24 -> 3236 | G43: ='BS 2026'!C24 -> 3120 | H43: =H4*(Assumptions!B38) -> 4485.1448 | I43: =I4*(Assumptions!C38) -> 4913.7072 | J43: =J4*(Assumptions!D38) -> 5359.7438 | K43: =K4*(Assumptions!E38) -> 5821.9426 | L43: =L4*(Assumptions!F38) -> 6298.8965
A44: Goodwill | C44: ='BS 2026'!G29 -> 47937 | D44: ='BS 2026'!F29 -> 48568 | E44: ='BS 2026'!E29 -> 48620 | F44: ='BS 2026'!D29 -> 51283 | G44: ='BS 2026'!C29 -> 57941 | H44: =G44+(-H94+G94) -> 58873.181 | I44: =H44+(-I94+H94) -> 59847.823 | J44: =I44+(-J94+I94) -> 60862.206 | K44: =J44+(-K94+J94) -> 61913.345 | L44: =K44+(-L94+K94) -> 62998.041
A45: Intangible assets | C45: ='BS 2026'!G30 -> 8978 | D45: ='BS 2026'!F30 -> 7125 | E45: ='BS 2026'!E30 -> 5278 | F45: ='BS 2026'!D30 -> 4428 | G45: ='BS 2026'!C30 -> 6815 | H45: =G45 -> 6815 | I45: =H45 -> 6815 | J45: =I45 -> 6815 | K45: =J45 -> 6815 | L45: =K45 -> 6815
A46: Operating lease right-of-use assets, net | C46: ='BS 2026'!G25 -> 2880 | D46: ='BS 2026'!F25 -> 2890 | E46: ='BS 2026'!E25 -> 2366 | F46: ='BS 2026'!D25 -> 2157 | G46: ='BS 2026'!C25 -> 2003 | H46: =G46 -> 2003 | I46: =H46 -> 2003 | J46: =I46 -> 2003 | K46: =J46 -> 2003 | L46: =K46 -> 2003
A47: Noncurrent costs capitalized to obtain revenue contracts, net | C47: ='BS 2026'!G26 -> 2342 | D47: ='BS 2026'!F26 -> 2697 | E47: ='BS 2026'!E26 -> 2515 | F47: ='BS 2026'!D26 -> 2475 | G47: ='BS 2026'!C26 -> 2985 | H47: =H4*$H$150 -> 3507.8329 | I47: =I4*$H$150 -> 3843.0116 | J47: =J4*$H$150 -> 4191.857 | K47: =K4*$H$150 -> 4553.3428 | L47: =L4*$H$150 -> 4926.3685
A48: Strategic Investments | C48: ='BS 2026'!G28 -> 4784 | D48: ='BS 2026'!F28 -> 4672 | E48: ='BS 2026'!E28 -> 4848 | F48: ='BS 2026'!D28 -> 4852 | G48: ='BS 2026'!C28 -> 7591 | H48: =G48 -> 7591 | I48: =H48 -> 7591 | J48: =I48 -> 7591 | K48: =J48 -> 7591 | L48: =K48 -> 7591
A49: Deferred Tax asset | C49: ='BS 2026'!G31 -> 2623 | D49: ='BS 2026'!F31 -> 2800 | E49: ='BS 2026'!E31 -> 3433 | F49: ='BS 2026'!D31 -> 4770 | G49: ='BS 2026'!C31 -> 3628 | H49: =H4*(Assumptions!B41) -> 4570.6251 | I49: =I4*(Assumptions!C41) -> 5007.3553 | J49: =J4*(Assumptions!D41) -> 5461.8928 | K49: =K4*(Assumptions!E41) -> 5932.9004 | L49: =L4*(Assumptions!F41) -> 6418.9443
A50: Total non-current assets | H50: =SUM(H43:H49) -> 87845.783 | I50: =SUM(I43:I49) -> 90020.898 | J50: =SUM(J43:J49) -> 92284.7 | K50: =SUM(K43:K49) -> 94630.531 | L50: =SUM(L43:L49) -> 97051.25
A51: Total Assets | C51: =C39+SUM(C43:C49) -> 95209 | D51: =D39+SUM(D43:D49) -> 98849 | E51: =E39+SUM(E43:E49) -> 99823 | F51: =F39+SUM(F43:F49) -> 102928 | G51: =G39+SUM(G43:G49) -> 112305 | H51: =H39+SUM(H43:H49) -> 114382.28 | I51: =I39+SUM(I43:I49) -> 120671.97 | J51: =J39+SUM(J43:J49) -> 128236.41 | ... L51: =L39+SUM(L43:L49) -> 147672.25
A52: Liabilities:
A53: Current Liabilities
A54: Accounts Payable | C54: ='BS 2026'!G35 -> 5470 | D54: ='BS 2026'!F35 -> 6743 | E54: ='BS 2026'!E35 -> 6111 | F54: ='BS 2026'!D35 -> 6658 | G54: ='BS 2026'!C35 -> 8253 | H54: =(Assumptions!B32*Forecasting!H6)/365 -> 8082.799 | I54: =(Assumptions!C32*Forecasting!I6)/365 -> 8855.1228 | J54: =(Assumptions!D32*Forecasting!J6)/365 -> 9658.9373 | K54: =(Assumptions!E32*Forecasting!K6)/365 -> 10491.878 | L54: =(Assumptions!F32*Forecasting!L6)/365 -> 11351.409
A55: Accrued expenses
A56: Other CL | C56: ='BS 2026'!G36+'BS 2026'!G37 -> 16314 | D56: ='BS 2026'!F36+'BS 2026'!F37 -> 17966 | E56: ='BS 2026'!E36+'BS 2026'!E37 -> 19521 | F56: ='BS 2026'!D36+'BS 2026'!D37 -> 21322 | G56: ='BS 2026'!C36+'BS 2026'!C37 -> 24865 | H56: =H4*$H$152 -> 26601.416 | I56: =I4*$H$152 -> 29143.222 | J56: =J4*$H$152 -> 31788.667 | K56: =K4*$H$152 -> 34529.971 | L56: =L4*$H$152 -> 37358.786
A57: Short term debt- current portion | C57: ='BS 2026'!G39 -> 4 | D57: ='BS 2026'!F39 -> 1182 | E57: ='BS 2026'!E39 -> 999 | F57: ='BS 2026'!D39 -> 0 | G57: ='BS 2026'!C39 -> 4000 | H57: =MAX(0,H75) -> 695.00851 | I57: =MAX(0,I75) -> 0 | J57: =MAX(0,J75) -> 0 | K57: =MAX(0,K75) -> 0 | L57: =MAX(0,L75) -> 0
A58: Total CL | C58: =SUM(C54:C57) -> 21788 | D58: =SUM(D54:D57) -> 25891 | E58: =SUM(E54:E57) -> 26631 | F58: =SUM(F54:F57) -> 27980 | G58: =SUM(G54:G57) -> 37118 | H58: =SUM(H54:H57) -> 35379.223 | I58: =SUM(I54:I57) -> 37998.345 | J58: =SUM(J54:J57) -> 41447.604 | ... L58: =SUM(L54:L57) -> 48710.196
A59: Non-current liabilities
A60: Long term debt | C60: ='BS 2026'!G41 -> 10592 | D60: ='BS 2026'!F41 -> 9419 | E60: ='BS 2026'!E41 -> 8427 | F60: ='BS 2026'!D41 -> 8433 | G60: ='BS 2026'!C41 -> 10439 | H60: =G60+H111 -> 10001 | I60: =H60+I111 -> 9476.2 | J60: =I60+J111 -> 8847.24 | K60: =J60+K111 -> 8328.888 | L60: =K60+L111 -> 7906.8656
A61: lease liabilities | C61: ='BS 2026'!G42 -> 2703 | D61: ='BS 2026'!F42 -> 2897 | E61: ='BS 2026'!E42 -> 2644 | F61: ='BS 2026'!D42 -> 2380 | G61: ='BS 2026'!C42 -> 2189 | H61: =G61*(1-0.05) -> 2079.55 | I61: =H61*(1-0.05) -> 1975.5725 | J61: =I61*(1-0.05) -> 1876.7939 | K61: =J61*(1-0.05) -> 1782.9542 | L61: =K61*(1-0.05) -> 1693.8065
A62: Deffered tax liability
A63: Other non-current liabilities | C63: ='BS 2026'!G43 -> 1995 | D63: ='BS 2026'!F43 -> 2283 | E63: ='BS 2026'!E43 -> 2475 | F63: ='BS 2026'!D43 -> 2962 | G63: ='BS 2026'!C43 -> 3417 | H63: =G63 -> 3417 | I63: =H63 -> 3417 | J63: =I63 -> 3417 | K63: =J63 -> 3417 | L63: =K63 -> 3417
A64: Total non-current Liabilities | C64: =SUM(C60:C63) -> 15290 | D64: =SUM(D60:D63) -> 14599 | E64: =SUM(E60:E63) -> 13546 | F64: =SUM(F60:F63) -> 13775 | G64: =SUM(G60:G63) -> 16045 | H64: =SUM(H60:H63) -> 15497.55 | I64: =SUM(I60:I63) -> 14868.773 | J64: =SUM(J60:J63) -> 14141.034 | ... L64: =SUM(L60:L63) -> 13017.672
A65: Total Liabilities | C65: =C64+C58 -> 37078 | D65: =D64+D58 -> 40490 | E65: =E64+E58 -> 40177 | F65: =F64+F58 -> 41755 | G65: =G64+G58 -> 53163 | H65: =H64+H58 -> 50876.773 | I65: =I64+I58 -> 52867.117 | J65: =J64+J58 -> 55588.638 | ... L65: =L64+L58 -> 61727.868
A66: Equity
A67: Common Stock | C67: ='BS 2026'!G52 -> 1 | D67: ='BS 2026'!F52 -> 1 | E67: ='BS 2026'!E52 -> 1 | F67: ='BS 2026'!D52 -> 1 | G67: ='BS 2026'!C52 -> 1 | H67: =G67 -> 1 | I67: =H67 -> 1 | J67: =I67 -> 1 | K67: =J67 -> 1 | L67: =K67 -> 1
A68: Additional paid -in capital | C68: ='BS 2026'!G55 -> 50919 | D68: ='BS 2026'!F55 -> 55047 | E68: ='BS 2026'!E55 -> 59841 | F68: ='BS 2026'!D55 -> 64576 | G68: ='BS 2026'!C55 -> 68835 | H68: =G68+H82+H109 -> 73840.44 | I68: =H68+I82+I109 -> 79324.158 | J68: =I68+J82+J109 -> 85305.655 | K68: =J68+K82+K109 -> 91802.967 | L68: =K68+L82+L109 -> 98832.562
A69: Retained earnings | C69: ='BS 2026'!G57 -> 7377 | D69: ='BS 2026'!F57 -> 7585 | E69: ='BS 2026'!E57 -> 11721 | F69: ='BS 2026'!D57 -> 16369 | G69: ='BS 2026'!C57 -> 22221 | H69: =G69+H27+H112 -> 27988.063 | I69: =H69+I27+I112 -> 34494.494 | J69: =I69+J27+J112 -> 41784.882 | K69: =J69+K27+K112 -> 49902.388 | L69: =K69+L27+L112 -> 58888.438
A70: Accumulated other comprehensive income (loss) | C70: ='BS 2026'!G56 -> -166 | D70: ='BS 2026'!F56 -> -274 | E70: ='BS 2026'!E56 -> -225 | F70: ='BS 2026'!D56 -> -266 | G70: ='BS 2026'!C56 -> 313 | H70: =G70 -> 313 | I70: =H70 -> 313 | J70: =I70 -> 313 | K70: =J70 -> 313 | L70: =K70 -> 313
A71: Treasury stock, at cost | D71: ='BS 2026'!F54 -> -4000 | E71: ='BS 2026'!E54 -> -11692 | F71: ='BS 2026'!D54 -> -19507 | G71: ='BS 2026'!C54 -> -32228 | H71: =G71+H106 -> -38637 | I71: =H71+I106 -> -46327.8 | J71: =I71+J106 -> -54756.76 | K71: =J71+K106 -> -63347.512 | L71: =K71+L106 -> -72090.614
A72: Total Equity | C72: =SUM(C67:C71) -> 58131 | D72: =SUM(D67:D71) -> 58359 | E72: =SUM(E67:E71) -> 59646 | F72: =SUM(F67:F71) -> 61173 | G72: =SUM(G67:G71) -> 59142 | H72: =SUM(H67:H71) -> 63505.504 | I72: =SUM(I67:I71) -> 67804.852 | J72: =SUM(J67:J71) -> 72647.776 | ... L72: =SUM(L67:L71) -> 85944.385
A73: Total Liabilities & Equity | C73: =C72+C65 -> 95209 | D73: =D72+D65 -> 98849 | E73: =E72+E65 -> 99823 | F73: =F72+F65 -> 102928 | G73: =G72+G65 -> 112305 | H73: =H72+H65 -> 114382.28 | I73: =I72+I65 -> 120671.97 | J73: =J72+J65 -> 128236.41 | ... L73: =L72+L65 -> 147672.25
A74: Check | H74: =H73-H51 -> 0 | I74: =I73-I51 -> 0 | J74: =J73-J51 -> 0 | K74: =K73-K51 -> 0 | L74: =L73-L51 -> 0
A75: Funding Gap | H75: =(H33+H35+H37+H38+H43+H44+H45+H46+H47+H48+H49) - (H54+H56+H60+H61+H63+H67+H68+H69+H70+H71) -> 695.00851 | I75: =(I33+I35+I37+I38+I43+I44+I45+I46+I47+I48+I49) - (I54+I56+I60+I61+I63+I67+I68+I69+I70+I71) -> -2167.6621 | J75: =(J33+J35+J37+J38+J43+J44+J45+J46+J47+J48+J49) - (J54+J56+J60+J61+J63+J67+J68+J69+J70+J71) -> -5136.3607 | K75: =(K33+K35+K37+K38+K43+K44+K45+K46+K47+K48+K49) - (K54+K56+K60+K61+K63+K67+K68+K69+K70+K71) -> -8267.8241 | L75: =(L33+L35+L37+L38+L43+L44+L45+L46+L47+L48+L49) - (L54+L56+L60+L61+L63+L67+L68+L69+L70+L71) -> -11690.226
A77: Cashflow statement
A78: Operating activities:
A79: Net Income | C79: ='CF26'!G16 -> 1444 | D79: ='CF26'!F16 -> 208 | E79: ='CF26'!E16 -> 4136 | F79: ='CF26'!D16 -> 6197 | G79: ='CF26'!C16 -> 7457 | H79: =H27 -> 7433.4132 | I79: =I27 -> 8256.0982 | J79: =J27 -> 9127.5387 | K79: =K27 -> 10046.514 | L79: =L27 -> 11011.509
A80: Depreciation & amortisation | C80: ='CF26'!G19 -> 3298 | D80: ='CF26'!F19 -> 3786 | E80: ='CF26'!E19 -> 3959 | F80: ='CF26'!D19 -> 3477 | G80: ='CF26'!C19 -> 3631 | H80: =H4*Assumptions!B26 -> 3996.208 | I80: =I4*Assumptions!C26 -> 4378.0517 | J80: =J4*Assumptions!D26 -> 4775.4648 | K80: =K4*Assumptions!E26 -> 5187.2782 | L80: =L4*Assumptions!F26 -> 5612.2381
A81: Amortization of costs capitalized to obtain revenue contracts, net | C81: ='CF26'!G21 -> 1348 | D81: ='CF26'!F21 -> 1668 | E81: ='CF26'!E21 -> 1925 | F81: ='CF26'!D21 -> 2095 | G81: ='CF26'!C21 -> 2197 | H81: =H4*$H$147 -> 2417.9755 | I81: =I4*$H$147 -> 2649.0167 | J81: =J4*$H$147 -> 2889.4784 | K81: =K4*$H$147 -> 3138.6533 | L81: =L4*$H$147 -> 3395.7827
A82: Stock-based compensation expense | C82: ='CF26'!G22 -> 2779 | D82: ='CF26'!F22 -> 3279 | E82: ='CF26'!E22 -> 2787 | F82: ='CF26'!D22 -> 3183 | G82: ='CF26'!C22 -> 3509 | H82: =H4*$H$149 -> 3861.9372 | I82: =I4*$H$149 -> 4230.9511 | J82: =J4*$H$149 -> 4615.0113 | K82: =K4*$H$149 -> 5012.9879 | L82: =L4*$H$149 -> 5423.6694
A83: (Gains) losses on strategic investments, net | C83: ='CF26'!G24 -> -1211 | D83: ='CF26'!F24 -> 239 | E83: ='CF26'!E24 -> 277 | F83: ='CF26'!D24 -> 121 | G83: ='CF26'!C24 -> -1017 | H83: =H22 -> 0 | I83: =I22 -> 0 | J83: =J22 -> 0 | K83: =K22 -> 0 | L83: =L22 -> 0
A84: Changes in working capital
A85: Ac/cs receivable, net | C85: ='CF26'!G28 -> -1824 | D85: ='CF26'!F28 -> -995 | E85: ='CF26'!E28 -> -659 | F85: ='CF26'!D28 -> -490 | G85: ='CF26'!C28 -> -2160 | H85: =-(H35-G35) -> -1187.0794 | I85: =-(I35-H35) -> -1483.5406 | J85: =-(J35-I35) -> -1544.0304 | K85: =-(K35-J35) -> -1599.9787 | L85: =-(L35-K35) -> -1651.0556
A86: Costs capitalized to obtain revenue contracts, net | C86: ='CF26'!G29 -> -2283 | D86: ='CF26'!F29 -> -2345 | E86: ='CF26'!E29 -> -1872 | F86: ='CF26'!D29 -> -2121 | G86: ='CF26'!C29 -> -2811 | H86: =G47-H47 -> -522.83286 | I86: =H47-I47 -> -335.17878 | J86: =I47-J47 -> -348.84534 | K86: =J47-K47 -> -361.48584 | L86: =K47-L47 -> -373.02572
A87: Prepaid expenses and other current assets and other assets | C87: ='CF26'!G30 -> 114 | D87: ='CF26'!F30 -> -302 | E87: ='CF26'!E30 -> -843 | F87: ='CF26'!D30 -> -1495 | G87: ='CF26'!C30 -> 819 | H87: =G37-H37+(G38-H38) -> -247.01813 | I87: =H37-I37+(H38-I38) -> -536.21869 | J87: =I37-J37+(I38-J38) -> -574.34533 | K87: =J37-K37+(J38-K38) -> -612.7356 | L87: =K37-L37+(K38-L38) -> -651.2305
A88: Accounts payable | C88: ='CF26'!G32 -> 507 | D88: ='CF26'!F32 -> 528 | E88: ='CF26'!E32 -> -478 | F88: ='CF26'!D32 -> 1089 | G88: ='CF26'!C32 -> 1014 | H88: =H54-G54 -> -170.20097 | I88: =I54-H54 -> 772.32377 | J88: =J54-I54 -> 803.81445 | K88: =K54-J54 -> 832.94087 | L88: =L54-K54 -> 859.53125
A89: Operating lease liabilities | C89: ='CF26'!G33 -> -801 | D89: ='CF26'!F33 -> -699 | E89: ='CF26'!E33 -> -621 | F89: ='CF26'!D33 -> -548 | G89: ='CF26'!C33 -> -567 | H89: =H61-G61 -> -109.45 | I89: =I61-H61 -> -103.9775 | J89: =J61-I61 -> -98.778625 | K89: =K61-J61 -> -93.839694 | L89: =L61-K61 -> -89.147709
A90: Unearned Revenue | C90: ='CF26'!G34 -> 2629 | D90: ='CF26'!F34 -> 1744 | E90: ='CF26'!E34 -> 1623 | F90: ='CF26'!D34 -> 1584 | G90: ='CF26'!C34 -> 2924 | H90: =H56-G56 -> 1736.4159 | I90: =I56-H56 -> 2541.8058 | J90: =J56-I56 -> 2645.4453 | K90: =K56-J56 -> 2741.3037 | L90: =L56-K56 -> 2828.8156
A91: CF from operating activities | C91: =SUM(C79:C90) -> 6000 | D91: =SUM(D79:D90) -> 7111 | E91: =SUM(E79:E90) -> 10234 | F91: =SUM(F79:F90) -> 13092 | G91: =SUM(G79:G90) -> 14996 | H91: =SUM(H79:H90) -> 17209.368 | I91: =SUM(I79:I90) -> 20369.332 | J91: =SUM(J79:J90) -> 22290.753 | ... L91: =SUM(L79:L90) -> 26367.087
A93: Investing activities
A94: Business combinations, net of cash acquired | C94: ='CF26'!G37 -> -14876 | D94: ='CF26'!F37 -> -439 | E94: ='CF26'!E37 -> -82 | F94: ='CF26'!D37 -> -2734 | G94: ='CF26'!C37 -> -9268 | H94: =G94/G4*H4 -> -10200.181 | I94: =H94/H4*I4 -> -11174.823 | J94: =I94/I4*J4 -> -12189.206 | K94: =J94/J4*K4 -> -13240.345 | L94: =K94/K4*L4 -> -14325.041
A95: Purchases of strategic investments | C95: ='CF26'!G38 -> -1718 | D95: ='CF26'!F38 -> -550 | E95: ='CF26'!E38 -> -496 | F95: ='CF26'!D38 -> -539 | G95: ='CF26'!C38 -> -1958 | H95: =MIN(0,H48-G48) -> 0 | I95: =MIN(0,I48-H48) -> 0 | J95: =MIN(0,J48-I48) -> 0 | K95: =MIN(0,K48-J48) -> 0 | L95: =MIN(0,L48-K48) -> 0
A96: Sales of strategic investments | C96: ='CF26'!G39 -> 2201 | D96: ='CF26'!F39 -> 355 | E96: ='CF26'!E39 -> 108 | F96: ='CF26'!D39 -> 126 | G96: ='CF26'!C39 -> 184 | H96: =MAX(0,H48-G48) -> 0 | I96: =MAX(0,I48-H48) -> 0 | J96: =MAX(0,J48-I48) -> 0 | K96: =MAX(0,K48-J48) -> 0 | L96: =MAX(0,L48-K48) -> 0
A97: Purchases of marketable securities | C97: ='CF26'!G40 -> -5674 | D97: ='CF26'!F40 -> -4777 | E97: ='CF26'!E40 -> -3761 | F97: ='CF26'!D40 -> -6879 | G97: ='CF26'!C40 -> -3763 | H97: =AVERAGE(C97:G97) -> -4970.8 | I97: =AVERAGE(D97:H97) -> -4830.16 | J97: =AVERAGE(E97:I97) -> -4840.792 | K97: =AVERAGE(F97:J97) -> -5056.7504 | L97: =AVERAGE(G97:K97) -> -4692.3005
A98: Sales of marketable securities | C98: ='CF26'!G41 -> 4179 | D98: ='CF26'!F41 -> 1771 | E98: ='CF26'!E41 -> 1511 | F98: ='CF26'!D41 -> 4143 | G98: ='CF26'!C41 -> 4414 | H98: =AVERAGE(C98:G98) -> 3203.6 | I98: =AVERAGE(D98:H98) -> 3008.52 | J98: =AVERAGE(E98:I98) -> 3256.024 | K98: =AVERAGE(F98:J98) -> 3605.0288 | L98: =AVERAGE(G98:K98) -> 3497.4346
A99: Maturities of marketable securities | C99: ='CF26'!G42 -> 2069 | D99: ='CF26'!F42 -> 2449 | E99: ='CF26'!E42 -> 2129 | F99: ='CF26'!D42 -> 3378 | G99: ='CF26'!C42 -> 2395 | H99: =AVERAGE(C99:G99) -> 2484 | I99: =AVERAGE(D99:H99) -> 2567 | J99: =AVERAGE(E99:I99) -> 2590.6 | K99: =AVERAGE(F99:J99) -> 2682.92 | L99: =AVERAGE(G99:K99) -> 2543.904
A100: Capex | C100: ='CF26'!G43 -> -717 | D100: ='CF26'!F43 -> -798 | E100: ='CF26'!E43 -> -736 | F100: ='CF26'!D43 -> -658 | G100: ='CF26'!C43 -> -594 | H100: =Assumptions!B28*Forecasting!H4 -> -653.74485 | I100: =Assumptions!C28*Forecasting!I4 -> -716.21116 | J100: =Assumptions!D28*Forecasting!J4 -> -781.22448 | K100: =Assumptions!E28*Forecasting!K4 -> -848.59357 | L100: =Assumptions!F28*Forecasting!L4 -> -918.11331
A101: CF from investing activities | C101: =SUM(C94:C100) -> -14536 | D101: =SUM(D94:D100) -> -1989 | E101: =SUM(E94:E100) -> -1327 | F101: =SUM(F94:F100) -> -3163 | G101: =SUM(G94:G100) -> -8590 | H101: =SUM(H94:H100) -> -10137.125 | I101: =SUM(I94:I100) -> -11145.675 | J101: =SUM(J94:J100) -> -11964.599 | ... L101: =SUM(L94:L100) -> -13894.116
A103: Financing Activities
A104: Proceeds from Debt issuance | C104: ='CF26'!G46 -> 7906 | D104: ='CF26'!F46 -> 0 | E104: ='CF26'!E46 -> 0 | F104: ='CF26'!D46 -> 0 | G104: ='CF26'!C46 -> 6000 | H104: 0 | I104: 0 | J104: 0 | K104: 0 | L104: 0
A106: Repurchases of common stock | C106: ='CF26'!G49 -> 0 | D106: ='CF26'!F49 -> -4000 | E106: ='CF26'!E49 -> -7620 | F106: ='CF26'!D49 -> -7829 | G106: ='CF26'!C49 -> -12596 | H106: =AVERAGE(C106:G106) -> -6409 | I106: =AVERAGE(D106:H106) -> -7690.8 | J106: =AVERAGE(E106:I106) -> -8428.96 | K106: =AVERAGE(F106:J106) -> -8590.752 | L106: =AVERAGE(G106:K106) -> -8743.1024
A107: Repayments of Slack Convertible Notes, net of capped call proceeds | C107: ='CF26'!G48 -> -1197 | D107: ='CF26'!F48 -> 0 | E107: ='CF26'!E48 -> 0 | F107: ='CF26'!D48 -> 0 | G107: ='CF26'!C48 -> 0 | H107: 0 | I107: 0 | J107: 0 | K107: 0 | L107: 0
...

Sheet Assumptions
A1: Scenarios
A2: Base-1 | B2: Historical Avg | D2: Annual Inflation assumption | E2: 0.02
A3: Bull-2 | B3: =5% -> 0.05
A4: Bear-3 | B4: =-5% -> -0.05
A6: Years | B6: 2027 | C6: 2028 | D6: 2029 | E6: 2030 | F6: 2031
A7: Timing as on | B7: January 31, 27 | C7: January 31, 28 | D7: January 31, 29 | E7: January 31, 30 | F7: January 31, 31
A8: Scenario Selector | B8: 1
A9: Revenue Growth- 1:Base | B9: =Forecasting!G120*(1+Assumptions!B3) -> 0.10058055 | C9: =B9*(1+$B$4) -> 0.095551524 | D9: =C9*(1+$B$4) -> 0.090773948 | E9: =D9*(1+$B$4) -> 0.08623525 | F9: =E9*(1+$B$4) -> 0.081923488
A10: Revenue Growth- 2:Bull | B10: =B9*(1+$B3) -> 0.10560958 | C10: =C9*(1+$B3) -> 0.1003291 | D10: =D9*(1+$B3) -> 0.095312645 | E10: =E9*(1+$B3) -> 0.090547013 | F10: =F9*(1+$B3) -> 0.086019662
A11: Revenue Growth- 3:Bear | B11: =B9*(1+$B$4) -> 0.095551524 | C11: =C9*(1+$B$4) -> 0.090773948 | D11: =D9*(1+$B$4) -> 0.08623525 | E11: =E9*(1+$B$4) -> 0.081923488 | F11: =F9*(1+$B$4) -> 0.077827313
A12: Active Growth% | B12: =CHOOSE($B$8, B9, B10, B11) -> 0.10058055 | C12: =CHOOSE($B$8, C9, C10, C11) -> 0.095551524 | D12: =CHOOSE($B$8, D9, D10, D11) -> 0.090773948 | E12: =CHOOSE($B$8, E9, E10, E11) -> 0.08623525 | F12: =CHOOSE($B$8, F9, F10, F11) -> 0.081923488
A13: COGS % of revenue- Base | B13: =Forecasting!H121 -> 0.21803901 | C13: =Forecasting!I121 -> 0.21283901 | D13: =Forecasting!J121 -> 0.20763901 | E13: =Forecasting!K121 -> 0.20243901 | F13: =Forecasting!L121 -> 0.19723901
A14: Active COGS % of revenue | B14: =CHOOSE($B$8,B13,B13*(1-$B$3),B13*(1-$B$4)) -> 0.21803901 | C14: =CHOOSE($B$8,C13,C13*(1-$B$3),C13*(1-$B$4)) -> 0.21283901 | D14: =CHOOSE($B$8,D13,D13*(1-$B$3),D13*(1-$B$4)) -> 0.20763901 | E14: =CHOOSE($B$8,E13,E13*(1-$B$3),E13*(1-$B$4)) -> 0.20243901 | F14: =CHOOSE($B$8,F13,F13*(1-$B$3),F13*(1-$B$4)) -> 0.19723901
A15: R&D % of revenue- Base | B15: =Forecasting!H122 -> 0.14360108 | C15: =Forecasting!I122 -> 0.14288308 | D15: =Forecasting!J122 -> 0.14216866 | E15: =Forecasting!K122 -> 0.14145782 | F15: =Forecasting!L122 -> 0.14075053
A16: Active R&D % of revenue | B16: =CHOOSE($B$8,B15,B15*(1-$B$3),B15*(1-$B$4)) -> 0.14360108 | C16: =CHOOSE($B$8,C15,C15*(1-$B$3),C15*(1-$B$4)) -> 0.14288308 | D16: =CHOOSE($B$8,D15,D15*(1-$B$3),D15*(1-$B$4)) -> 0.14216866 | E16: =CHOOSE($B$8,E15,E15*(1-$B$3),E15*(1-$B$4)) -> 0.14145782 | F16: =CHOOSE($B$8,F15,F15*(1-$B$3),F15*(1-$B$4)) -> 0.14075053
A17: Sales & marketing % of revenue- Base | B17: =Forecasting!H123 -> 0.34372727 | C17: =Forecasting!I123 -> 0.34200864 | D17: =Forecasting!J123 -> 0.34029859 | E17: =Forecasting!K123 -> 0.3385971 | F17: =Forecasting!L123 -> 0.33690411
A18: Active Sales & marketing % of revenue | B18: =CHOOSE($B$8,B17,B17*(1-$B$3),B17*(1-$B$4)) -> 0.34372727 | C18: =CHOOSE($B$8,C17,C17*(1-$B$3),C17*(1-$B$4)) -> 0.34200864 | D18: =CHOOSE($B$8,D17,D17*(1-$B$3),D17*(1-$B$4)) -> 0.34029859 | E18: =CHOOSE($B$8,E17,E17*(1-$B$3),E17*(1-$B$4)) -> 0.3385971 | F18: =CHOOSE($B$8,F17,F17*(1-$B$3),F17*(1-$B$4)) -> 0.33690411
A19: G&A % of revenue- Base | B19: =Forecasting!H124 -> 0.071884407 | C19: =Forecasting!I124 -> 0.071524985 | D19: =Forecasting!J124 -> 0.07116736 | E19: =Forecasting!K124 -> 0.070811523 | F19: =Forecasting!L124 -> 0.070457466
A20: Active G&A % of revenue | B20: =CHOOSE($B$8,B19,B19*(1-$B$3),B19*(1-$B$4)) -> 0.071884407 | C20: =CHOOSE($B$8,C19,C19*(1-$B$3),C19*(1-$B$4)) -> 0.071524985 | D20: =CHOOSE($B$8,D19,D19*(1-$B$3),D19*(1-$B$4)) -> 0.07116736 | E20: =CHOOSE($B$8,E19,E19*(1-$B$3),E19*(1-$B$4)) -> 0.070811523 | F20: =CHOOSE($B$8,F19,F19*(1-$B$3),F19*(1-$B$4)) -> 0.070457466
A21: Other opex % revenue- Base | B21: =Forecasting!H125 -> 0.014041421 | C21: =Forecasting!I125 -> 0.013971214 | D21: =Forecasting!J125 -> 0.013901358 | E21: =Forecasting!K125 -> 0.013831851 | F21: =Forecasting!L125 -> 0.013762692
A22: Active Other opex % revenue | B22: =CHOOSE($B$8,B21,B21*(1-$B$3),B21*(1-$B$4)) -> 0.014041421 | C22: =CHOOSE($B$8,C21,C21*(1-$B$3),C21*(1-$B$4)) -> 0.013971214 | D22: =CHOOSE($B$8,D21,D21*(1-$B$3),D21*(1-$B$4)) -> 0.013901358 | E22: =CHOOSE($B$8,E21,E21*(1-$B$3),E21*(1-$B$4)) -> 0.013831851 | F22: =CHOOSE($B$8,F21,F21*(1-$B$3),F21*(1-$B$4)) -> 0.013762692
A23: Other Income - Base | B23: =Forecasting!G126 -> 0.0041420831 | C23: =B23 -> 0.0041420831 | D23: =C23 -> 0.0041420831 | E23: =D23 -> 0.0041420831 | F23: =E23 -> 0.0041420831
A24: Other Income - Active | B24: =CHOOSE($B$8,B23,B23*(1+$B$3),B23*(1+$B$4)) -> 0.0041420831 | C24: =CHOOSE($B$8,C23,C23*(1+$B$3),C23*(1+$B$4)) -> 0.0041420831 | D24: =CHOOSE($B$8,D23,D23*(1+$B$3),D23*(1+$B$4)) -> 0.0041420831 | E24: =CHOOSE($B$8,E23,E23*(1+$B$3),E23*(1+$B$4)) -> 0.0041420831 | F24: =CHOOSE($B$8,F23,F23*(1+$B$3),F23*(1+$B$4)) -> 0.0041420831
A25: D & A % of revenue-Base | B25: =Forecasting!G127 -> 0.0874413 | C25: =B25 -> 0.0874413 | D25: =C25 -> 0.0874413 | E25: =D25 -> 0.0874413 | F25: =E25 -> 0.0874413
A26: Active D & A % of revenue | B26: =CHOOSE($B$8,B25,B25*(1-$B$3),B25*(1-$B$4)) -> 0.0874413 | C26: =CHOOSE($B$8,C25,C25*(1-$B$3),C25*(1-$B$4)) -> 0.0874413 | D26: =CHOOSE($B$8,D25,D25*(1-$B$3),D25*(1-$B$4)) -> 0.0874413 | E26: =CHOOSE($B$8,E25,E25*(1-$B$3),E25*(1-$B$4)) -> 0.0874413 | F26: =CHOOSE($B$8,F25,F25*(1-$B$3),F25*(1-$B$4)) -> 0.0874413
A27: Capex % of revenue-Base | B27: =Forecasting!G128 -> -0.014304636 | C27: =B27 -> -0.014304636 | D27: =C27 -> -0.014304636 | E27: =D27 -> -0.014304636 | F27: =E27 -> -0.014304636
A28: Active Capex % of revenue | B28: =CHOOSE($B$8,B27,B27*(1-$B$3),B27*(1-$B$4)) -> -0.014304636 | C28: =CHOOSE($B$8,C27,C27*(1-$B$3),C27*(1-$B$4)) -> -0.014304636 | D28: =CHOOSE($B$8,D27,D27*(1-$B$3),D27*(1-$B$4)) -> -0.014304636 | E28: =CHOOSE($B$8,E27,E27*(1-$B$3),E27*(1-$B$4)) -> -0.014304636 | F28: =CHOOSE($B$8,F27,F27*(1-$B$3),F27*(1-$B$4)) -> -0.014304636
A29: AR days- Base | B29: =AVERAGE(Forecasting!C129:G129) -> 124.00043 | C29: =B29 -> 124.00043 | D29: =C29 -> 124.00043 | E29: =D29 -> 124.00043 | F29: =E29 -> 124.00043
A30: Active AR days | B30: =CHOOSE($B$8,B29,B29*(1-$B$3),B29*(1-$B$4)) -> 124.00043 | C30: =CHOOSE($B$8,C29,C29*(1-$B$3),C29*(1-$B$4)) -> 124.00043 | D30: =CHOOSE($B$8,D29,D29*(1-$B$3),D29*(1-$B$4)) -> 124.00043 | E30: =CHOOSE($B$8,E29,E29*(1-$B$3),E29*(1-$B$4)) -> 124.00043 | F30: =CHOOSE($B$8,F29,F29*(1-$B$3),F29*(1-$B$4)) -> 124.00043
A31: AP days- Base | B31: =AVERAGE(Forecasting!C130:G130) -> 289.16989 | C31: =B31 -> 289.16989 | D31: =C31 -> 289.16989 | E31: =D31 -> 289.16989 | F31: =E31 -> 289.16989
A32: Active AP days | B32: =CHOOSE($B$8,B31,B31*(1+$B$3),B31*(1+$B$4)) -> 289.16989 | C32: =CHOOSE($B$8,C31,C31*(1+$B$3),C31*(1+$B$4)) -> 289.16989 | D32: =CHOOSE($B$8,D31,D31*(1+$B$3),D31*(1+$B$4)) -> 289.16989 | E32: =CHOOSE($B$8,E31,E31*(1+$B$3),E31*(1+$B$4)) -> 289.16989 | F32: =CHOOSE($B$8,F31,F31*(1+$B$3),F31*(1+$B$4)) -> 289.16989
A33: Active Tax rate% | B33: =Forecasting!G132 -> 0.21670168 | C33: =B33 -> 0.21670168 | D33: =C33 -> 0.21670168 | E33: =D33 -> 0.21670168 | F33: =E33 -> 0.21670168
A34: Prepaid expenses- Base | B34: =AVERAGE(Forecasting!C134:G134) -> 0.046254375 | C34: =B34*(1+0.02) -> 0.047179462 | D34: =C34*(1+0.02) -> 0.048123052 | E34: =D34*(1+0.02) -> 0.049085513 | F34: =E34*(1+0.02) -> 0.050067223
A35: Active Prepaid expenses | B35: =CHOOSE($B$8,B34,B34*(1-$B$3),B34*(1-$B$4)) -> 0.046254375 | C35: =CHOOSE($B$8,C34,C34*(1-$B$3),C34*(1-$B$4)) -> 0.047179462 | D35: =CHOOSE($B$8,D34,D34*(1-$B$3),D34*(1-$B$4)) -> 0.048123052 | E35: =CHOOSE($B$8,E34,E34*(1-$B$3),E34*(1-$B$4)) -> 0.049085513 | F35: =CHOOSE($B$8,F34,F34*(1-$B$3),F34*(1-$B$4)) -> 0.050067223
A36: Other CA | B36: =AVERAGE(Forecasting!C135:G135) -> 0.053633099 | C36: =B36*(1+$E$2) -> 0.054705761 | D36: =C36*(1+$E$2) -> 0.055799877 | E36: =D36*(1+$E$2) -> 0.056915874 | F36: =E36*(1+$E$2) -> 0.058054192
A37: Active Other CA | B37: =CHOOSE($B$8,B36,B36*(1-$B$3),B36*(1-$B$4)) -> 0.053633099 | C37: =CHOOSE($B$8,C36,C36*(1-$B$3),C36*(1-$B$4)) -> 0.054705761 | D37: =CHOOSE($B$8,D36,D36*(1-$B$3),D36*(1-$B$4)) -> 0.055799877 | E37: =CHOOSE($B$8,E36,E36*(1-$B$3),E36*(1-$B$4)) -> 0.056915874 | F37: =CHOOSE($B$8,F36,F36*(1-$B$3),F36*(1-$B$4)) -> 0.058054192
A38: Active Net PPE | B38: =AVERAGE(Forecasting!C136:G136) -> 0.09813976 | C38: =B38 -> 0.09813976 | D38: =C38 -> 0.09813976 | E38: =D38 -> 0.09813976 | F38: =E38 -> 0.09813976
A39: Active intangible Assets | B39: =AVERAGE(Forecasting!D137:G137) -> -0.021899442 | C39: =B39 -> -0.021899442 | D39: =C39 -> -0.021899442 | E39: =D39 -> -0.021899442 | F39: =E39 -> -0.021899442
A40: Active non-curretn assets | B40: =AVERAGE(Forecasting!C138:G138) -> 0.1559053 | C40: =B40 -> 0.1559053 | D40: =C40 -> 0.1559053 | E40: =D40 -> 0.1559053 | F40: =E40 -> 0.1559053
A41: Active Deferred Tax asset | B41: =AVERAGE(Forecasting!C139:G139) -> 0.10001016 | C41: =B41 -> 0.10001016 | D41: =C41 -> 0.10001016 | E41: =D41 -> 0.10001016 | F41: =E41 -> 0.10001016
A42: Active lease liability | B42: =Forecasting!G142-0.05% -> 0.052215232 | C42: =B42 -> 0.052215232 | D42: =C42 -> 0.052215232 | E42: =D42 -> 0.052215232 | F42: =E42 -> 0.052215232
A43: Active Other non-current liabilities | B43: =AVERAGE(Forecasting!C143:G143) -> 0.14471022 | C43: =B43 -> 0.14471022 | D43: =C43 -> 0.14471022 | E43: =D43 -> 0.14471022 | F43: =E43 -> 0.14471022
A44: Active Accumulated other comprehensive income (loss) | B44: =AVERAGE(Forecasting!C145:G145) -> -0.0041884458 | C44: =B44 -> -0.0041884458 | D44: =C44 -> -0.0041884458 | E44: =D44 -> -0.0041884458 | F44: =E44 -> -0.0041884458
A45: Active Treasury stock, at cost | B45: =AVERAGE(Forecasting!C146:G146) -> -0.35077729 | C45: =AVERAGE(Forecasting!D146:H146) -> -0.43847161 | D45: =AVERAGE(Forecasting!E146:I146) -> -0.54210095 | E45: =AVERAGE(Forecasting!F146:J146) -> -0.64543763 | F45: =AVERAGE(Forecasting!G146:K146) -> -0.77611078
A47: Strategic investments held at cost, no activity assumed. As historical gains/losses are non-operating, unpredictable mark-to-market swings on strategic investments (e.g. +$1,017M FY26, -$121M FY25). Held flat at zero as a conservative, non-speculative assumption.
